{"data":{"invoices":[{"id":"INV-1774021899199","date":"2026-03-20","amount":100,"client":"Test Client","status":"paid","booking":"Test real flow","currency":"USD"}],"payLinks":[{"id":"LINK-MMZ2TZX6","url":"https://zenipay.ca/pay/LINK-MMZ2TZX6?amount=100&currency=USD&desc=Test%20real%20flow&m=Zeniva%20Travel","uses":0,"amount":100,"status":"active","currency":"USD","createdAt":"2026-03-20T15:51:36.474Z","description":"Test real flow"}],"transactions":[{"id":"ZNV-MMZ2U1WH","amount":100,"status":"succeeded","currency":"USD","createdAt":"2026-03-20T15:51:39.041Z","card_last4":"4242","description":"Test real flow","pay_link_id":"LINK-MMZ2TZX6","customer_name":"Test Client"}]}}